{"v":"5.10.2","fr":60,"ip":0,"op":179,"w":430,"h":430,"nm":"wired-flat-958-faq-frequent-ask-questions","ddd":0,"assets":[{"id":"comp_1","nm":"hover-enlarge","fr":60,"layers":[{"ddd":0,"ind":1,"ty":0,"nm":"chat-1","refId":"comp_2","sr":1,"ks":{"o":{"a":0,"k":100,"ix":11},"r":{"a":0,"k":0,"ix":10},"p":{"a":0,"k":[215,215,0],"ix":2,"l":2},"a":{"a":0,"k":[215,215,0],"ix":1,"l":2},"s":{"a":0,"k":[100,100,100],"ix":6,"l":2}},"ao":0,"w":430,"h":430,"ip":69,"op":844,"st":0,"bm":0},{"ddd":0,"ind":2,"ty":0,"nm":"chat-2","refId":"comp_3","sr":1,"ks":{"o":{"a":0,"k":100,"ix":11},"r":{"a":0,"k":0,"ix":10},"p":{"a":0,"k":[215,215,0],"ix":2,"l":2},"a":{"a":0,"k":[215,215,0],"ix":1,"l":2},"s":{"a":0,"k":[100,100,100],"ix":6,"l":2}},"ao":0,"w":430,"h":430,"ip":69,"op":844,"st":0,"bm":0},{"ddd":0,"ind":3,"ty":0,"nm":"chat-2","refId":"comp_3","sr":1,"ks":{"o":{"a":0,"k":100,"ix":11},"r":{"a":0,"k":0,"ix":10},"p":{"a":0,"k":[215,215,0],"ix":2,"l":2},"a":{"a":0,"k":[215,215,0],"ix":1,"l":2},"s":{"a":0,"k":[100,100,100],"ix":6,"l":2}},"ao":0,"w":430,"h":430,"ip":0,"op":70,"st":0,"bm":0},{"ddd":0,"ind":4,"ty":0,"nm":"chat-1","refId":"comp_2","sr":1,"ks":{"o":{"a":0,"k":100,"ix":11},"r":{"a":0,"k":0,"ix":10},"p":{"a":0,"k":[215,215,0],"ix":2,"l":2},"a":{"a":0,"k":[215,215,0],"ix":1,"l":2},"s":{"a":0,"k":[100,100,100],"ix":6,"l":2}},"ao":0,"w":430,"h":430,"ip":0,"op":70,"st":0,"bm":0}]},{"id":"comp_2","nm":"chat-1","fr":60,"layers":[{"ddd":0,"ind":1,"ty":4,"nm":"outline 4","parent":2,"sr":1,"ks":{"o":{"a":0,"k":100,"ix":11},"r":{"a":0,"k":0,"ix":10},"p":{"a":0,"k":[-2.213,0.108,0],"ix":2,"l":2},"a":{"a":0,"k":[207.996,160.107,0],"ix":1,"l":2},"s":{"a":0,"k":[100,100,100],"ix":6,"l":2}},"ao":0,"shapes":[{"ty":"gr","it":[{"ind":0,"ty":"sh","ix":1,"ks":{"a":1,"k":[{"i":{"x":0.25,"y":1},"o":{"x":0.59,"y":0},"t":52,"s":[{"i":[[0,0],[0,0]],"o":[[0,0],[0,0]],"v":[[-10.48,-9.673],[10.48,9.673]],"c":false}]},{"i":{"x":0.667,"y":1},"o":{"x":0.835,"y":0},"t":85,"s":[{"i":[[0,0],[0,0]],"o":[[0,0],[0,0]],"v":[[46.124,-27.888],[81.359,4.635]],"c":false}]},{"i":{"x":0.25,"y":1},"o":{"x":0.333,"y":0},"t":136,"s":[{"i":[[0,0],[0,0]],"o":[[0,0],[0,0]],"v":[[-30.871,-2.421],[-13.777,13.358]],"c":false}]},{"t":166,"s":[{"i":[[0,0],[0,0]],"o":[[0,0],[0,0]],"v":[[-10.48,-9.673],[10.48,9.673]],"c":false}]}],"ix":2},"nm":"Path 1","mn":"ADBE Vector Shape - Group","hd":false},{"ty":"st","c":{"a":0,"k":[0.933,0.4,0.667,1],"ix":3,"x":"var $bm_rt;\n$bm_rt = comp('wired-flat-958-faq-frequent-ask-questions').layer('control').effect('tertiary')('Color');"},"o":{"a":0,"k":100,"ix":4},"w":{"a":0,"k":7,"ix":5},"lc":2,"lj":2,"bm":0,"nm":".tertiary","mn":"ADBE Vector Graphic - Stroke","hd":false,"cl":"tertiary"},{"ty":"tr","p":{"a":0,"k":[228.512,181.886],"ix":2},"a":{"a":0,"k":[0,0],"ix":1},"s":{"a":0,"k":[100,100],"ix":3},"r":{"a":0,"k":0,"ix":6},"o":{"a":0,"k":100,"ix":7},"sk":{"a":0,"k":0,"ix":4},"sa":{"a":0,"k":0,"ix":5},"nm":"Transform"}],"nm":"Group 1","np":2,"cix":2,"bm":0,"ix":1,"mn":"ADBE Vector Group","hd":false},{"ty":"gr","it":[{"ind":0,"ty":"sh","ix":1,"ks":{"a":1,"k":[{"i":{"x":0.25,"y":1},"o":{"x":0.59,"y":0},"t":52,"s":[{"i":[[0,-17.379],[-16.584,0],[0,17.379],[16.584,0]],"o":[[0,17.379],[16.584,0],[0,-17.379],[-16.584,0]],"v":[[-30.029,0],[0,31.467],[30.029,0],[0,-31.467]],"c":true}]},{"i":{"x":0.667,"y":1},"o":{"x":0.835,"y":0},"t":85,"s":[{"i":[[0,-29.214],[-27.879,0],[0,29.214],[27.879,0]],"o":[[0,29.214],[27.879,0],[0,-29.214],[-27.879,0]],"v":[[-1.369,-26.459],[49.111,26.438],[99.59,-26.459],[49.111,-79.357]],"c":true}]},{"i":{"x":0.25,"y":1},"o":{"x":0.333,"y":0},"t":136,"s":[{"i":[[0,-14.174],[-13.526,0],[0,14.174],[13.526,0]],"o":[[0,14.174],[13.526,0],[0,-14.174],[-13.526,0]],"v":[[-42.852,9.486],[-18.362,35.149],[6.129,9.486],[-18.362,-16.178]],"c":true}]},{"t":166,"s":[{"i":[[0,-17.379],[-16.584,0],[0,17.379],[16.584,0]],"o":[[0,17.379],[16.584,0],[0,-17.379],[-16.584,0]],"v":[[-30.029,0],[0,31.467],[30.029,0],[0,-31.467]],"c":true}]}],"ix":2},"nm":"Path 1","mn":"ADBE Vector Shape - Group","hd":false},{"ty":"st","c":{"a":0,"k":[0.933,0.4,0.667,1],"ix":3,"x":"var $bm_rt;\n$bm_rt = comp('wired-flat-958-faq-frequent-ask-questions').layer('control').effect('tertiary')('Color');"},"o":{"a":0,"k":100,"ix":4},"w":{"a":0,"k":7,"ix":5},"lc":2,"lj":2,"bm":0,"nm":".tertiary","mn":"ADBE Vector Graphic - Stroke","hd":false,"cl":"tertiary"},{"ty":"tr","p":{"a":0,"k":[207.028,160.107],"ix":2},"a":{"a":0,"k":[0,0],"ix":1},"s":{"a":0,"k":[100,100],"ix":3},"r":{"a":0,"k":0,"ix":6},"o":{"a":0,"k":100,"ix":7},"sk":{"a":0,"k":0,"ix":4},"sa":{"a":0,"k":0,"ix":5},"nm":"Transform"}],"nm":"Group 2","np":2,"cix":2,"bm":0,"ix":2,"mn":"ADBE Vector Group","hd":false}],"ip":0,"op":844,"st":0,"ct":1,"bm":0},{"ddd":0,"ind":2,"ty":4,"nm":"Chat-1","sr":1,"ks":{"o":{"a":0,"k":100,"ix":11},"r":{"a":1,"k":[{"i":{"x":[0.667],"y":[1]},"o":{"x":[0.333],"y":[0]},"t":52,"s":[0]},{"i":{"x":[0.07],"y":[1]},"o":{"x":[0.333],"y":[0]},"t":70,"s":[-4]},{"i":{"x":[0.667],"y":[1]},"o":{"x":[0.93],"y":[0]},"t":117,"s":[12]},{"i":{"x":[0.667],"y":[1]},"o":{"x":[0.333],"y":[0]},"t":144,"s":[-8]},{"t":179,"s":[0]}],"ix":10},"p":{"a":1,"k":[{"i":{"x":0.07,"y":1},"o":{"x":0.333,"y":0},"t":52,"s":[55.119,195.226,0],"to":[0,0,0],"ti":[0,0,0]},{"i":{"x":0.667,"y":1},"o":{"x":0.93,"y":0},"t":107.457,"s":[55.119,218.226,0],"to":[0,0,0],"ti":[0,0,0]},{"i":{"x":0.667,"y":1},"o":{"x":0.333,"y":0},"t":141,"s":[55.119,185.226,0],"to":[0,0,0],"ti":[0,0,0]},{"t":173,"s":[55.119,195.226,0]}],"ix":2,"l":2},"a":{"a":0,"k":[-120.089,70.226,0],"ix":1,"l":2},"s":{"a":0,"k":[100,100,100],"ix":6,"l":2}},"ao":0,"shapes":[{"ty":"gr","it":[{"ind":0,"ty":"sh","ix":1,"ks":{"a":1,"k":[{"i":{"x":0.16,"y":1},"o":{"x":0.707,"y":0},"t":52,"s":[{"i":[[-38.785,0],[0,0],[0,-38.785],[0,0],[38.785,0],[0,0],[0,0]],"o":[[0,0],[38.785,0],[0,0],[0,38.785],[0,0],[0,0],[0,-38.785]],"v":[[-49.863,-70.226],[49.863,-70.226],[120.089,0],[120.089,0],[49.863,70.226],[-120.089,70.226],[-120.089,0]],"c":true}]},{"i":{"x":0.667,"y":1},"o":{"x":0.863,"y":0},"t":84.789,"s":[{"i":[[-55.378,0],[0,0],[0,-55.378],[0,0],[55.378,0],[0,0],[0,0]],"o":[[0,0],[55.378,0],[0,0],[0,55.378],[0,0],[0,0],[0,-55.378]],"v":[[-19.818,-130.316],[122.574,-130.316],[222.846,-30.045],[222.846,-30.045],[122.574,70.226],[-120.089,70.226],[-120.089,-30.045]],"c":true}]},{"i":{"x":0.266,"y":1},"o":{"x":0.333,"y":0},"t":136,"s":[{"i":[[-32.255,0],[0,0],[0,-32.255],[0,0],[32.255,0],[0,0],[0,0]],"o":[[0,0],[32.255,0],[0,0],[0,32.255],[0,0],[0,0],[0,-32.255]],"v":[[-61.686,-46.58],[21.251,-46.58],[79.654,11.823],[79.654,11.823],[21.251,70.226],[-120.089,70.226],[-120.089,11.823]],"c":true}]},{"t":166,"s":[{"i":[[-38.785,0],[0,0],[0,-38.785],[0,0],[38.785,0],[0,0],[0,0]],"o":[[0,0],[38.785,0],[0,0],[0,38.785],[0,0],[0,0],[0,-38.785]],"v":[[-49.863,-70.226],[49.863,-70.226],[120.089,0],[120.089,0],[49.863,70.226],[-120.089,70.226],[-120.089,0]],"c":true}]}],"ix":2},"nm":"Path 1","mn":"ADBE Vector Shape - Group","hd":false},{"ty":"tr","p":{"a":0,"k":[0,0],"ix":2},"a":{"a":0,"k":[0,0],"ix":1},"s":{"a":0,"k":[100,100],"ix":3},"r":{"a":0,"k":0,"ix":6},"o":{"a":0,"k":100,"ix":7},"sk":{"a":0,"k":0,"ix":4},"sa":{"a":0,"k":0,"ix":5},"nm":"Transform"}],"nm":"Group 1","np":1,"cix":2,"bm":0,"ix":1,"mn":"ADBE Vector Group","hd":false}],"ip":0,"op":844,"st":0,"ct":1,"bm":0},{"ddd":0,"ind":3,"ty":4,"nm":"White fill","parent":2,"sr":1,"ks":{"o":{"a":0,"k":100,"ix":11},"r":{"a":0,"k":-0.047,"ix":10},"p":{"a":0,"k":[-0.271,0.009,0],"ix":2,"l":2},"a":{"a":0,"k":[209.996,160.108,0],"ix":1,"l":2},"s":{"a":0,"k":[100,100,100],"ix":6,"l":2}},"ao":0,"shapes":[{"ty":"gr","it":[{"ind":0,"ty":"sh","ix":1,"ks":{"a":1,"k":[{"i":{"x":0.185,"y":1},"o":{"x":0.658,"y":0},"t":52,"s":[{"i":[[0,0],[0,-38.78],[0,0],[0,0],[0,0],[-38.78,0]],"o":[[-38.78,0],[0,0],[0,0],[0,0],[0,-38.78],[0,0]],"v":[[44.11,-70.225],[-26.11,-0.005],[-26.11,70.225],[-44.11,70.225],[-44.11,-0.005],[26.11,-70.225]],"c":true}]},{"i":{"x":0.667,"y":1},"o":{"x":0.871,"y":0},"t":85,"s":[{"i":[[0,0],[0,-55.394],[0,0],[0,0],[0,0],[-55.394,0]],"o":[[-55.394,0],[0,0],[0,0],[0,0],[0,-55.394],[0,0]],"v":[[81.906,-130.396],[-18.397,-30.092],[-18.397,70.225],[-44.108,70.225],[-44.108,-30.092],[56.195,-130.396]],"c":true}]},{"i":{"x":0.218,"y":1},"o":{"x":0.333,"y":0},"t":136,"s":[{"i":[[0,0],[0,-32.316],[0,0],[0,0],[0,0],[-32.316,0]],"o":[[-32.316,0],[0,0],[0,0],[0,0],[0,-32.316],[0,0]],"v":[[29.406,-46.816],[-29.111,11.701],[-29.111,70.225],[-44.111,70.225],[-44.111,11.701],[14.406,-46.816]],"c":true}]},{"t":166,"s":[{"i":[[0,0],[0,-38.78],[0,0],[0,0],[0,0],[-38.78,0]],"o":[[-38.78,0],[0,0],[0,0],[0,0],[0,-38.78],[0,0]],"v":[[44.11,-70.225],[-26.11,-0.005],[-26.11,70.225],[-44.11,70.225],[-44.11,-0.005],[26.11,-70.225]],"c":true}]}],"ix":2},"nm":"Path 1","mn":"ADBE Vector Shape - Group","hd":false},{"ty":"fl","c":{"a":0,"k":[1,1,1,1],"ix":4,"x":"var $bm_rt;\n$bm_rt = comp('wired-flat-958-faq-frequent-ask-questions').layer('control').effect('primary')('Color');"},"o":{"a":0,"k":100,"ix":5},"r":1,"bm":0,"nm":".primary","mn":"ADBE Vector Graphic - Fill","hd":false,"cl":"primary"},{"ty":"tr","p":{"a":0,"k":[134.02,160.11],"ix":2},"a":{"a":0,"k":[0,0],"ix":1},"s":{"a":0,"k":[100,100],"ix":3},"r":{"a":0,"k":0,"ix":6},"o":{"a":0,"k":50,"ix":7},"sk":{"a":0,"k":0,"ix":4},"sa":{"a":0,"k":0,"ix":5},"nm":"Transform"}],"nm":"Group 1","np":2,"cix":2,"bm":1,"ix":1,"mn":"ADBE Vector Group","hd":false},{"ty":"gr","it":[{"ind":0,"ty":"sh","ix":1,"ks":{"a":1,"k":[{"i":{"x":0.185,"y":1},"o":{"x":0.658,"y":0},"t":52,"s":[{"i":[[-38.785,0],[0,0],[0,-38.785],[0,0],[38.785,0],[0,0],[0,0]],"o":[[0,0],[38.785,0],[0,0],[0,38.785],[0,0],[0,0],[0,-38.785]],"v":[[-49.863,-70.226],[49.863,-70.226],[120.089,0],[120.089,0],[49.863,70.226],[-120.089,70.226],[-120.089,0]],"c":true}]},{"i":{"x":0.667,"y":1},"o":{"x":0.871,"y":0},"t":85,"s":[{"i":[[-55.401,0],[0,0],[0,-55.401],[0,0],[55.401,0],[0,0],[0,0]],"o":[[0,0],[55.401,0],[0,0],[0,55.401],[0,0],[0,0],[0,-55.401]],"v":[[-19.777,-130.399],[122.673,-130.399],[222.986,-30.087],[222.986,-30.086],[122.673,70.226],[-120.089,70.226],[-120.089,-30.087]],"c":true}]},{"i":{"x":0.218,"y":1},"o":{"x":0.333,"y":0},"t":136,"s":[{"i":[[-32.32,0],[0,0],[0,-32.32],[0,0],[32.32,0],[0,0],[0,0]],"o":[[0,0],[32.32,0],[0,0],[0,32.32],[0,0],[0,0],[0,-32.32]],"v":[[-61.568,-46.816],[21.537,-46.816],[80.058,11.705],[80.058,11.705],[21.537,70.226],[-120.089,70.226],[-120.089,11.705]],"c":true}]},{"t":166,"s":[{"i":[[-38.785,0],[0,0],[0,-38.785],[0,0],[38.785,0],[0,0],[0,0]],"o":[[0,0],[38.785,0],[0,0],[0,38.785],[0,0],[0,0],[0,-38.785]],"v":[[-49.863,-70.226],[49.863,-70.226],[120.089,0],[120.089,0],[49.863,70.226],[-120.089,70.226],[-120.089,0]],"c":true}]}],"ix":2},"nm":"Path 1","mn":"ADBE Vector Shape - Group","hd":false},{"ty":"fl","c":{"a":0,"k":[1,1,1,1],"ix":4,"x":"var $bm_rt;\n$bm_rt = comp('wired-flat-958-faq-frequent-ask-questions').layer('control').effect('primary')('Color');"},"o":{"a":0,"k":100,"ix":5},"r":1,"bm":0,"nm":".primary","mn":"ADBE Vector Graphic - Fill","hd":false,"cl":"primary"},{"ty":"tr","p":{"a":0,"k":[209.996,160.107],"ix":2},"a":{"a":0,"k":[0,0],"ix":1},"s":{"a":0,"k":[100,100],"ix":3},"r":{"a":0,"k":0,"ix":6},"o":{"a":0,"k":100,"ix":7},"sk":{"a":0,"k":0,"ix":4},"sa":{"a":0,"k":0,"ix":5},"nm":"Transform"}],"nm":"Group 4","np":2,"cix":2,"bm":0,"ix":2,"mn":"ADBE Vector Group","hd":false}],"ip":0,"op":844,"st":0,"ct":1,"bm":0}]},{"id":"comp_3","nm":"chat-2","fr":60,"layers":[{"ddd":0,"ind":1,"ty":4,"nm":"outline 8","parent":2,"sr":1,"ks":{"o":{"a":0,"k":100,"ix":11},"r":{"a":0,"k":0,"ix":10},"p":{"a":0,"k":[0,4,0],"ix":2,"l":2},"a":{"a":0,"k":[290.03,341,0],"ix":1,"l":2},"s":{"a":0,"k":[100,100,100],"ix":6,"l":2}},"ao":0,"shapes":[{"ty":"gr","it":[{"ind":0,"ty":"sh","ix":1,"ks":{"a":1,"k":[{"i":{"x":0.24,"y":1},"o":{"x":0.333,"y":0},"t":0,"s":[{"i":[[0,0],[0,0]],"o":[[0,0],[0,0]],"v":[[20.812,0],[-20.812,0]],"c":false}]},{"i":{"x":0.667,"y":1},"o":{"x":0.76,"y":0},"t":30,"s":[{"i":[[0,0],[0,0]],"o":[[0,0],[0,0]],"v":[[-20.635,-12.961],[-94.349,-12.961]],"c":false}]},{"i":{"x":0.24,"y":1},"o":{"x":0.333,"y":0},"t":76,"s":[{"i":[[0,0],[0,0]],"o":[[0,0],[0,0]],"v":[[32.981,5.372],[3.108,5.372]],"c":false}]},{"t":103,"s":[{"i":[[0,0],[0,0]],"o":[[0,0],[0,0]],"v":[[20.812,0],[-20.812,0]],"c":false}]}],"ix":2},"nm":"Path 1","mn":"ADBE Vector Shape - Group","hd":false},{"ty":"st","c":{"a":0,"k":[1,1,1,1],"ix":3,"x":"var $bm_rt;\n$bm_rt = comp('wired-flat-958-faq-frequent-ask-questions').layer('control').effect('primary')('Color');"},"o":{"a":0,"k":100,"ix":4},"w":{"a":0,"k":7,"ix":5},"lc":2,"lj":2,"bm":0,"nm":".primary","mn":"ADBE Vector Graphic - Stroke","hd":false,"cl":"primary"},{"ty":"tr","p":{"a":0,"k":[292.255,352.928],"ix":2},"a":{"a":0,"k":[0,0],"ix":1},"s":{"a":0,"k":[100,100],"ix":3},"r":{"a":0,"k":0,"ix":6},"o":{"a":0,"k":100,"ix":7},"sk":{"a":0,"k":0,"ix":4},"sa":{"a":0,"k":0,"ix":5},"nm":"Transform"}],"nm":"Group 1","np":2,"cix":2,"bm":0,"ix":1,"mn":"ADBE Vector Group","hd":false},{"ty":"gr","it":[{"ind":0,"ty":"sh","ix":1,"ks":{"a":1,"k":[{"i":{"x":0.24,"y":1},"o":{"x":0.333,"y":0},"t":0,"s":[{"i":[[0,0],[0,0],[0,0]],"o":[[0,0],[0,0],[0,0]],"v":[[27.604,31.363],[0.916,-31.363],[-27.604,31.363]],"c":false}]},{"i":{"x":0.667,"y":1},"o":{"x":0.76,"y":0},"t":30,"s":[{"i":[[0,0],[0,0],[0,0]],"o":[[0,0],[0,0],[0,0]],"v":[[-8.781,30.3],[-56.043,-80.781],[-106.552,30.3]],"c":false}]},{"i":{"x":0.24,"y":1},"o":{"x":0.333,"y":0},"t":76,"s":[{"i":[[0,0],[0,0],[0,0]],"o":[[0,0],[0,0],[0,0]],"v":[[37.919,32.377],[18.766,-12.639],[-1.703,32.377]],"c":false}]},{"t":103,"s":[{"i":[[0,0],[0,0],[0,0]],"o":[[0,0],[0,0],[0,0]],"v":[[27.604,31.363],[0.916,-31.363],[-27.604,31.363]],"c":false}]}],"ix":2},"nm":"Path 1","mn":"ADBE Vector Shape - Group","hd":false},{"ty":"st","c":{"a":0,"k":[1,1,1,1],"ix":3,"x":"var $bm_rt;\n$bm_rt = comp('wired-flat-958-faq-frequent-ask-questions').layer('control').effect('primary')('Color');"},"o":{"a":0,"k":100,"ix":4},"w":{"a":0,"k":7,"ix":5},"lc":2,"lj":2,"bm":0,"nm":".primary","mn":"ADBE Vector Graphic - Stroke","hd":false,"cl":"primary"},{"ty":"tr","p":{"a":0,"k":[292.03,336.999],"ix":2},"a":{"a":0,"k":[0,0],"ix":1},"s":{"a":0,"k":[100,100],"ix":3},"r":{"a":0,"k":0,"ix":6},"o":{"a":0,"k":100,"ix":7},"sk":{"a":0,"k":0,"ix":4},"sa":{"a":0,"k":0,"ix":5},"nm":"Transform"}],"nm":"Group 2","np":2,"cix":2,"bm":0,"ix":2,"mn":"ADBE Vector Group","hd":false}],"ip":0,"op":844,"st":0,"ct":1,"bm":0},{"ddd":0,"ind":2,"ty":4,"nm":"Chat-2","sr":1,"ks":{"o":{"a":0,"k":100,"ix":11},"r":{"a":1,"k":[{"i":{"x":[0.667],"y":[1]},"o":{"x":[0.568],"y":[0]},"t":0,"s":[0]},{"i":{"x":[0.229],"y":[1]},"o":{"x":[0.333],"y":[0]},"t":10,"s":[-14.878]},{"i":{"x":[0.667],"y":[1]},"o":{"x":[0.94],"y":[0]},"t":49,"s":[22]},{"i":{"x":[0.667],"y":[1]},"o":{"x":[0.333],"y":[0]},"t":84,"s":[-3]},{"t":113,"s":[0]}],"ix":10},"p":{"a":1,"k":[{"i":{"x":0.06,"y":1},"o":{"x":0.333,"y":0},"t":0,"s":[375.119,372.226,0],"to":[0,0,0],"ti":[0,0,0]},{"i":{"x":0.667,"y":1},"o":{"x":0.94,"y":0},"t":41,"s":[375.119,348.226,0],"to":[0,0,0],"ti":[0,0,0]},{"i":{"x":0.667,"y":1},"o":{"x":0.333,"y":0},"t":81.148,"s":[375.119,378.226,0],"to":[0,0,0],"ti":[0,0,0]},{"t":107.4609375,"s":[375.119,372.226,0]}],"ix":2,"l":2},"a":{"a":0,"k":[120.089,70.226,0],"ix":1,"l":2},"s":{"a":0,"k":[100,100,100],"ix":6,"l":2}},"ao":0,"shapes":[{"ty":"gr","it":[{"ind":0,"ty":"sh","ix":1,"ks":{"a":1,"k":[{"i":{"x":0.21,"y":1},"o":{"x":0.333,"y":0},"t":0,"s":[{"i":[[38.785,0],[0,0],[0,-38.785],[0,0],[-38.785,0],[0,0],[0,0]],"o":[[0,0],[-38.785,0],[0,0],[0,38.785],[0,0],[0,0],[0,-38.785]],"v":[[49.863,-70.226],[-49.863,-70.226],[-120.089,0],[-120.089,0],[-49.863,70.226],[120.089,70.226],[120.089,0]],"c":true}]},{"i":{"x":0.667,"y":1},"o":{"x":0.79,"y":0},"t":30,"s":[{"i":[[55.696,0],[0,0],[0,-55.696],[0,0],[-55.696,0],[0,0],[0,0]],"o":[[0,0],[-55.696,0],[0,0],[0,55.696],[0,0],[0,0],[0,-55.696]],"v":[[19.243,-131.467],[-123.966,-131.467],[-224.812,-30.62],[-224.812,-30.62],[-123.966,70.226],[120.089,70.226],[120.089,-30.62]],"c":true}]},{"i":{"x":0.21,"y":1},"o":{"x":0.333,"y":0},"t":76,"s":[{"i":[[33.723,0],[0,0],[0,-33.723],[0,0],[-33.723,0],[0,0],[0,0]],"o":[[0,0],[-33.723,0],[0,0],[0,33.723],[0,0],[0,0],[0,-33.723]],"v":[[59.029,-51.895],[-27.681,-51.895],[-88.742,9.166],[-88.742,9.166],[-27.681,70.226],[120.089,70.226],[120.089,9.166]],"c":true}]},{"t":103,"s":[{"i":[[38.785,0],[0,0],[0,-38.785],[0,0],[-38.785,0],[0,0],[0,0]],"o":[[0,0],[-38.785,0],[0,0],[0,38.785],[0,0],[0,0],[0,-38.785]],"v":[[49.863,-70.226],[-49.863,-70.226],[-120.089,0],[-120.089,0],[-49.863,70.226],[120.089,70.226],[120.089,0]],"c":true}]}],"ix":2},"nm":"Path 1","mn":"ADBE Vector Shape - Group","hd":false},{"ty":"tr","p":{"a":0,"k":[0,0],"ix":2},"a":{"a":0,"k":[0,0],"ix":1},"s":{"a":0,"k":[100,100],"ix":3},"r":{"a":0,"k":0,"ix":6},"o":{"a":0,"k":100,"ix":7},"sk":{"a":0,"k":0,"ix":4},"sa":{"a":0,"k":0,"ix":5},"nm":"Transform"}],"nm":"Group 1","np":1,"cix":2,"bm":0,"ix":1,"mn":"ADBE Vector Group","hd":false}],"ip":0,"op":844,"st":0,"ct":1,"bm":0},{"ddd":0,"ind":3,"ty":4,"nm":"Blue fill","parent":2,"sr":1,"ks":{"o":{"a":0,"k":100,"ix":11},"r":{"a":0,"k":0,"ix":10},"p":{"a":0,"k":[0,0,0],"ix":2,"l":2},"a":{"a":0,"k":[290.03,336.999,0],"ix":1,"l":2},"s":{"a":0,"k":[100,100,100],"ix":6,"l":2}},"ao":0,"shapes":[{"ty":"gr","it":[{"ind":0,"ty":"sh","ix":1,"ks":{"a":1,"k":[{"i":{"x":0.192,"y":1},"o":{"x":0.333,"y":0},"t":0,"s":[{"i":[[-12.71,-12.71],[-19.39,0],[0,0],[12.71,12.71],[0,19.4],[-38.79,0],[0,0],[0,-38.78]],"o":[[12.71,12.71],[0,0],[-19.39,0],[-12.71,-12.71],[0,-38.78],[0,0],[-38.79,0],[0,19.4]],"v":[[-5.545,49.655],[44.115,70.225],[26.115,70.225],[-23.545,49.655],[-44.115,-0.005],[26.115,-70.225],[44.115,-70.225],[-26.115,-0.005]],"c":true}]},{"i":{"x":0.667,"y":1},"o":{"x":0.821,"y":0},"t":30,"s":[{"i":[[-18.238,-18.238],[-27.823,0],[0,0],[18.238,18.238],[0,27.837],[-55.66,0],[0,0],[0,-55.646]],"o":[[18.238,18.238],[0,0],[-27.823,0],[-18.238,-18.238],[0,-55.646],[0,0],[-55.66,0],[0,27.837]],"v":[[-93.228,40.708],[-21.97,70.225],[-47.798,70.225],[-119.056,40.708],[-148.572,-30.549],[-47.798,-131.309],[-21.97,-131.309],[-122.744,-30.549]],"c":true}]},{"i":{"x":0.176,"y":1},"o":{"x":0.333,"y":0},"t":76,"s":[{"i":[[-11.031,-11.031],[-16.828,0],[0,0],[11.031,11.031],[0,16.837],[-33.665,0],[0,0],[0,-33.656]],"o":[[11.031,11.031],[0,0],[-16.828,0],[-11.031,-11.031],[0,-33.656],[0,0],[-33.665,0],[0,16.837]],"v":[[21.094,52.373],[64.192,70.225],[48.571,70.225],[5.473,52.373],[-12.38,9.275],[48.571,-51.667],[64.192,-51.667],[3.242,9.275]],"c":true}]},{"t":103,"s":[{"i":[[-12.71,-12.71],[-19.39,0],[0,0],[12.71,12.71],[0,19.4],[-38.79,0],[0,0],[0,-38.78]],"o":[[12.71,12.71],[0,0],[-19.39,0],[-12.71,-12.71],[0,-38.78],[0,0],[-38.79,0],[0,19.4]],"v":[[-5.545,49.655],[44.115,70.225],[26.115,70.225],[-23.545,49.655],[-44.115,-0.005],[26.115,-70.225],[44.115,-70.225],[-26.115,-0.005]],"c":true}]}],"ix":2},"nm":"Path 1","mn":"ADBE Vector Shape - Group","hd":false},{"ty":"fl","c":{"a":0,"k":[0.4,0.843,0.933,1],"ix":4,"x":"var $bm_rt;\n$bm_rt = comp('wired-flat-958-faq-frequent-ask-questions').layer('control').effect('secondary')('Color');"},"o":{"a":0,"k":100,"ix":5},"r":1,"bm":0,"nm":".secondary","mn":"ADBE Vector Graphic - Fill","hd":false,"cl":"secondary"},{"ty":"tr","p":{"a":0,"k":[214.055,337],"ix":2},"a":{"a":0,"k":[0,0],"ix":1},"s":{"a":0,"k":[100,100],"ix":3},"r":{"a":0,"k":0,"ix":6},"o":{"a":0,"k":50,"ix":7},"sk":{"a":0,"k":0,"ix":4},"sa":{"a":0,"k":0,"ix":5},"nm":"Transform"}],"nm":"Group 1","np":2,"cix":2,"bm":1,"ix":1,"mn":"ADBE Vector Group","hd":false},{"ty":"gr","it":[{"ind":0,"ty":"sh","ix":1,"ks":{"a":1,"k":[{"i":{"x":0.192,"y":1},"o":{"x":0.333,"y":0},"t":0,"s":[{"i":[[38.785,0],[0,0],[0,-38.785],[0,0],[-38.785,0],[0,0],[0,2.209],[0,0]],"o":[[0,0],[-38.785,0],[0,0],[0,38.785],[0,0],[2.209,0],[0,0],[0,-38.785]],"v":[[49.863,-70.226],[-49.863,-70.226],[-120.089,0],[-120.089,0],[-49.863,70.226],[116.089,70.226],[120.089,66.226],[120.089,0]],"c":true}]},{"i":{"x":0.667,"y":1},"o":{"x":0.821,"y":0},"t":30,"s":[{"i":[[55.653,0],[0,0],[0,-55.653],[0,0],[-55.653,0],[0,0],[0,3.17],[0,0]],"o":[[0,0],[-55.653,0],[0,0],[0,55.653],[0,0],[3.17,0],[0,0],[0,-55.653]],"v":[[19.321,-131.311],[-123.778,-131.311],[-224.547,-30.542],[-224.547,-30.542],[-123.778,70.226],[114.35,70.226],[120.089,64.487],[120.089,-30.542]],"c":true}]},{"i":{"x":0.176,"y":1},"o":{"x":0.333,"y":0},"t":76,"s":[{"i":[[33.66,0],[0,0],[0,-33.66],[0,0],[-33.66,0],[0,0],[0,1.917],[0,0]],"o":[[0,0],[-33.66,0],[0,0],[0,33.66],[0,0],[1.917,0],[0,0],[0,-33.66]],"v":[[59.142,-51.668],[-27.407,-51.668],[-88.354,9.279],[-88.354,9.279],[-27.407,70.226],[116.618,70.226],[120.089,66.755],[120.089,9.279]],"c":true}]},{"t":103,"s":[{"i":[[38.785,0],[0,0],[0,-38.785],[0,0],[-38.785,0],[0,0],[0,2.209],[0,0]],"o":[[0,0],[-38.785,0],[0,0],[0,38.785],[0,0],[2.209,0],[0,0],[0,-38.785]],"v":[[49.863,-70.226],[-49.863,-70.226],[-120.089,0],[-120.089,0],[-49.863,70.226],[116.089,70.226],[120.089,66.226],[120.089,0]],"c":true}]}],"ix":2},"nm":"Path 1","mn":"ADBE Vector Shape - Group","hd":false},{"ty":"fl","c":{"a":0,"k":[0.4,0.843,0.933,1],"ix":4,"x":"var $bm_rt;\n$bm_rt = comp('wired-flat-958-faq-frequent-ask-questions').layer('control').effect('secondary')('Color');"},"o":{"a":0,"k":100,"ix":5},"r":1,"bm":0,"nm":".secondary","mn":"ADBE Vector Graphic - Fill","hd":false,"cl":"secondary"},{"ty":"tr","p":{"a":0,"k":[290.03,336.999],"ix":2},"a":{"a":0,"k":[0,0],"ix":1},"s":{"a":0,"k":[100,100],"ix":3},"r":{"a":0,"k":0,"ix":6},"o":{"a":0,"k":100,"ix":7},"sk":{"a":0,"k":0,"ix":4},"sa":{"a":0,"k":0,"ix":5},"nm":"Transform"}],"nm":"Group 2","np":2,"cix":2,"bm":0,"ix":2,"mn":"ADBE Vector Group","hd":false}],"ip":-1,"op":844,"st":0,"ct":1,"bm":0}]}],"layers":[{"ddd":0,"ind":1,"ty":3,"nm":"control","sr":1,"ks":{"o":{"a":0,"k":0,"ix":11},"r":{"a":0,"k":0,"ix":10},"p":{"a":0,"k":[0,0],"ix":2,"l":2},"a":{"a":0,"k":[0,0,0],"ix":1,"l":2},"s":{"a":0,"k":[100,100,100],"ix":6,"l":2}},"ao":0,"ef":[{"ty":5,"nm":"primary","np":3,"mn":"ADBE Color Control","ix":1,"en":1,"ef":[{"ty":2,"nm":"Color","mn":"ADBE Color Control-0001","ix":1,"v":{"a":0,"k":[1,1,1],"ix":1}}]},{"ty":5,"nm":"secondary","np":3,"mn":"ADBE Color Control","ix":2,"en":1,"ef":[{"ty":2,"nm":"Color","mn":"ADBE Color Control-0001","ix":1,"v":{"a":0,"k":[0.4,0.843,0.933],"ix":1}}]},{"ty":5,"nm":"tertiary","np":3,"mn":"ADBE Color Control","ix":3,"en":1,"ef":[{"ty":2,"nm":"Color","mn":"ADBE Color Control-0001","ix":1,"v":{"a":0,"k":[0.933,0.4,0.667],"ix":1}}]}],"ip":0,"op":470,"st":0,"bm":0},{"ddd":0,"ind":3,"ty":0,"nm":"hover-enlarge","refId":"comp_1","sr":1,"ks":{"o":{"a":0,"k":100,"ix":11},"r":{"a":0,"k":0,"ix":10},"p":{"a":0,"k":[215,215,0],"ix":2,"l":2},"a":{"a":0,"k":[215,215,0],"ix":1,"l":2},"s":{"a":0,"k":[100,100,100],"ix":6,"l":2}},"ao":0,"w":430,"h":430,"ip":0,"op":189,"st":0,"bm":0}],"markers":[{"tm":0,"cm":"default:hover-enlarge","dr":179}]}